MANIFEST.in
README.rst
setup.py
zcbot_web_core/__init__.py
zcbot_web_core.egg-info/PKG-INFO
zcbot_web_core.egg-info/SOURCES.txt
zcbot_web_core.egg-info/dependency_links.txt
zcbot_web_core.egg-info/top_level.txt
zcbot_web_core/auth/__init__.py
zcbot_web_core/auth/auth_cache_pool.py
zcbot_web_core/auth/share_auth.py
zcbot_web_core/client/__init__.py
zcbot_web_core/client/async_mongo_client.py
zcbot_web_core/client/async_mulit_tenant_mongo_client.py
zcbot_web_core/client/async_multi_database_mongo_client.py
zcbot_web_core/client/async_redis_client.py
zcbot_web_core/client/minio_client.py
zcbot_web_core/client/mongo_client.py
zcbot_web_core/client/multi_database_mongo_client.py
zcbot_web_core/client/multi_tenant_mongo_client.py
zcbot_web_core/client/mysql_client.py
zcbot_web_core/client/oss2_client.py
zcbot_web_core/client/rabbit_client.py
zcbot_web_core/client/redis_client.py
zcbot_web_core/client/zcbot_celery_client.py
zcbot_web_core/client/zcbot_predict_client.py
zcbot_web_core/context/__init__.py
zcbot_web_core/context/context_vars.py
zcbot_web_core/exception/__init__.py
zcbot_web_core/exception/exceptions.py
zcbot_web_core/lib/__init__.py
zcbot_web_core/lib/cfg.py
zcbot_web_core/lib/func.py
zcbot_web_core/lib/logger.py
zcbot_web_core/lib/secret.py
zcbot_web_core/lib/settings.py
zcbot_web_core/lib/time.py
zcbot_web_core/lib/util.py
zcbot_web_core/middleware/__init__.py
zcbot_web_core/middleware/auth.py
zcbot_web_core/model/__init__.py
zcbot_web_core/model/base.py
zcbot_web_core/model/enums.py
zcbot_web_core/model/handler.py
zcbot_web_core/model/items.py
zcbot_web_core/model/query.py
zcbot_web_core/scheduler/__init__.py
zcbot_web_core/scheduler/simple_server.py
zcbot_web_core/service/__init__.py
zcbot_web_core/service/multi_process.py
zcbot_web_core/service/multi_thread.py
zcbot_web_core/service/thread_pool.py
zcbot_web_core/utils/__init__.py
zcbot_web_core/utils/common.py
zcbot_web_core/utils/context_var.py
zcbot_web_core/utils/decator.py
zcbot_web_core/utils/encryption.py
zcbot_web_core/utils/excel_exporter.py