Metadata-Version: 2.1
Name: zcbot-web-core
Version: 2.0.12
Summary: zcbot web core for zsodata
Home-page: http://www.zsodata.com
Author: zsodata
Author-email: team@zso.io
License: BSD License
Platform: all
Requires-Python: >=3.7
